{
  "display": {
    "icon": {
      "id": "minecraft:phantom_membrane"
    },
    "title": {
      "translate": "Night bird"
    },
    "description": {
      "translate": "Kill and get the phantom membrane. The winning mob in the voting 2017!",
      "color": "yellow"
    },
    "frame": "goal",
    "show_toast": true,
    "announce_to_chat": true,
    "hidden": false
  },
  "parent": "convenient_achievements:convenient_achievements",
  "criteria": {
    "Kill Phantom": {
      "trigger": "minecraft:player_killed_entity",
      "conditions": {
        "entity": {
          "type": "minecraft:phantom"
        }
      }
    },
    "Give Phantom Membrane": {
      "trigger": "minecraft:inventory_changed",
      "conditions": {
        "items": [
          {
            "items": "minecraft:phantom_membrane"
          }
        ]
      }
    }
  },
  "rewards": {
    "experience": 50
  }
}
